{
    "path_global_planner": [
        {
            "pose": [
                0.04980998143270199,
                0.002360240107179834,
                0.04734946514114483
            ],
            "footprint_cost": 0.0,
            "min_dist_to_obstacle": 0.800000011920929
        },
        {
            "pose": [
                0.09925546663247822,
                0.00957318933510326,
                0.14485506090706032
            ],
            "footprint_cost": 0.0,
            "min_dist_to_obstacle": 0.8015609890382592
        },
        {
            "pose": [
                0.14773408810414257,
                0.021685410577013398,
                0.24483432987885106
            ],
            "footprint_cost": 0.0,
            "min_dist_to_obstacle": 0.8558621511845242
        },
        {
            "pose": [
                0.1947616641336184,
                0.03857593265295173,
                0.3448135988506394
            ],
            "footprint_cost": 0.0,
            "min_dist_to_obstacle": 0.8631338379432997
        },
        {
            "pose": [
                0.2398685053675456,
                0.06007606095729401,
                0.44479286782243005
            ],
            "footprint_cost": 0.0,
            "min_dist_to_obstacle": 0.8732124728405286
        },
        {
            "pose": [
                0.28260410585005674,
                0.08597106230128093,
                0.54477213679422
            ],
            "footprint_cost": 0.0,
            "min_dist_to_obstacle": 0.9340770985323035
        },
        {
            "pose": [
                0.32254164246478484,
                0.11600230956730612,
                0.6447514057660095
            ],
            "footprint_cost": 0.0,
            "min_dist_to_obstacle": 0.9340770985323035
        },
        {
            "pose": [
                0.359282237843787,
                0.14986986475516012,
                0.7447306747377997
            ],
            "footprint_cost": 0.0,
            "min_dist_to_obstacle": 0.9962429571037404
        },
        {
            "pose": [
                0.3924589441674517,
                0.18723547462197748,
                0.8447099437095897
            ],
            "footprint_cost": 0.0,
            "min_dist_to_obstacle": 1.0594810208083518
        },
        {
            "pose": [
                0.4217404080670658,
                0.22772594899684118,
                0.9446892126813792
            ],
            "footprint_cost": 0.0,
            "min_dist_to_obstacle": 1.1067971975514959
        },
        {
            "pose": [
                0.4474080270108863,
                0.2706156512850389,
                1.0315125631829836
            ],
            "footprint_cost": 0.0,
            "min_dist_to_obstacle": 1.1704700085133246
        },
        {
            "pose": [
                0.4726078863132192,
                0.3137886999879423,
                1.0424526526343645
            ],
            "footprint_cost": 0.0,
            "min_dist_to_obstacle": 1.1704700085133246
        },
        {
            "pose": [
                0.49915673676861055,
                0.3579834247383902,
                1.0298443339515166
            ],
            "footprint_cost": 0.0,
            "min_dist_to_obstacle": 1.2349089219244234
        },
        {
            "pose": [
                0.5251274735033407,
                0.4035214642947948,
                1.0524948869910846
            ],
            "footprint_cost": 0.0,
            "min_dist_to_obstacle": 1.2816005808949662
        },
        {
            "pose": [
                0.5509673392348792,
                0.44975103999447075,
                1.0611102574258877
            ],
            "footprint_cost": 0.0,
            "min_dist_to_obstacle": 1.346291221844928
        },
        {
            "pose": [
                0.5770275300427572,
                0.4959524186592643,
                1.0572252201384733
            ],
            "footprint_cost": 0.0,
            "min_dist_to_obstacle": 1.3928388484733278
        },
        {
            "pose": [
                0.6036464452737851,
                0.541434117647535,
                1.0412807218528335
            ],
            "footprint_cost": 0.0,
            "min_dist_to_obstacle": 1.4577379954333136
        },
        {
            "pose": [
                0.6312002078598435,
                0.5856494133723827,
                1.0135121470856865
            ],
            "footprint_cost": 0.0,
            "min_dist_to_obstacle": 1.5231546438695542
        },
        {
            "pose": [
                0.6600844270540929,
                0.6283626295248954,
                0.976197950484115
            ],
            "footprint_cost": 0.0,
            "min_dist_to_obstacle": 1.5692355060309524
        },
        {
            "pose": [
                0.6905689102920471,
                0.6695879901555458,
                0.9340753589635143
            ],
            "footprint_cost": 0.0,
            "min_dist_to_obstacle": 1.589024881885386
        },
        {
            "pose": [
                0.7227306854232615,
                0.7095299099965663,
                0.8928844646443458
            ],
            "footprint_cost": 0.0,
            "min_dist_to_obstacle": 1.6347782967872762
        },
        {
            "pose": [
                0.7564588133603566,
                0.7485326104743617,
                0.8577932490962471
            ],
            "footprint_cost": 0.0,
            "min_dist_to_obstacle": 1.7007351605124235
        },
        {
            "pose": [
                0.7915072262648787,
                0.7869932740755703,
                0.8317843126502095
            ],
            "footprint_cost": 0.0,
            "min_dist_to_obstacle": 1.7670597310384706
        },
        {
            "pose": [
                0.8275713818036046,
                0.8252376106881784,
                0.8147293442417282
            ],
            "footprint_cost": 0.0,
            "min_dist_to_obstacle": 1.8124569230468983
        },
        {
            "pose": [
                0.8644013216661155,
                0.863540270421382,
                0.8049972629151919
            ],
            "footprint_cost": 0.0,
            "min_dist_to_obstacle": 1.8337121094136641
        },
        {
            "pose": [
                0.901856911480938,
                0.9021812895946311,
                0.8009748559431351
            ],
            "footprint_cost": 0.0,
            "min_dist_to_obstacle": 1.8200274994406525
        },
        {
            "pose": [
                0.9399235841481127,
                0.9415058057441565,
                0.801649790501604
            ],
            "footprint_cost": 0.0,
            "min_dist_to_obstacle": 1.750000026077032
        },
        {
            "pose": [
                0.9787083825792217,
                0.9819709148411779,
                0.8065976699905567
            ],
            "footprint_cost": 0.0,
            "min_dist_to_obstacle": 1.7204650790454523
        },
        {
            "pose": [
                1.0184146513857912,
                1.02415128136585,
                0.8156026684331951
            ],
            "footprint_cost": 0.0,
            "min_dist_to_obstacle": 1.65075742652012
        },
        {
            "pose": [
                1.0592699398575824,
                1.0686458573017599,
                0.8280119896243345
            ],
            "footprint_cost": 0.0,
            "min_dist_to_obstacle": 1.6101242428031823
        },
        {
            "pose": [
                1.1013724768896007,
                1.1158114794108955,
                0.8420551667230065
            ],
            "footprint_cost": 0.0,
            "min_dist_to_obstacle": 1.5402922030270783
        },
        {
            "pose": [
                1.1444994777692044,
                1.1653787117950292,
                0.8547649230556174
            ],
            "footprint_cost": 0.0,
            "min_dist_to_obstacle": 1.470544138898089
        },
        {
            "pose": [
                1.188357083919095,
                1.2167783032951716,
                0.8644083078002849
            ],
            "footprint_cost": 0.0,
            "min_dist_to_obstacle": 1.4008925934871161
        },
        {
            "pose": [
                1.2326925494320626,
                1.2694368875916757,
                0.870999080127916
            ],
            "footprint_cost": 0.0,
            "min_dist_to_obstacle": 1.331352715408136
        },
        {
            "pose": [
                1.2773227526284099,
                1.3229012076340316,
                0.8752130650377438
            ],
            "footprint_cost": 0.0,
            "min_dist_to_obstacle": 1.2776932529571765
        },
        {
            "pose": [
                1.3221271935984085,
                1.376855602789207,
                0.8777838953728131
            ],
            "footprint_cost": 0.0,
            "min_dist_to_obstacle": 1.2093386802653328
        },
        {
            "pose": [
                1.3670313663183509,
                1.4310969117448793,
                0.8792973297998519
            ],
            "footprint_cost": 0.0,
            "min_dist_to_obstacle": 1.1412712380575991
        },
        {
            "pose": [
                1.41199120312277,
                1.485501276397122,
                0.8801630679642336
            ],
            "footprint_cost": 0.0,
            "min_dist_to_obstacle": 1.0735455436762693
        },
        {
            "pose": [
                1.4569815087973061,
                1.5399961162113947,
                0.880646296450764
            ],
            "footprint_cost": 0.0,
            "min_dist_to_obstacle": 1.0062306048689096
        },
        {
            "pose": [
                1.5019882464684982,
                1.5945401573774998,
                0.8809100672410691
            ],
            "footprint_cost": 0.0,
            "min_dist_to_obstacle": 0.9394147254011668
        },
        {
            "pose": [
                1.5470037969107273,
                1.6491104533735357,
                0.8810501895475632
            ],
            "footprint_cost": 0.0,
            "min_dist_to_obstacle": 0.8732124728405286
        },
        {
            "pose": [
                1.5920241836942268,
                1.7036943815281274,
                0.8811200634893055
            ],
            "footprint_cost": 0.0,
            "min_dist_to_obstacle": 0.8077747331069568
        },
        {
            "pose": [
                1.63704750015619,
                1.7582849200168158,
                0.8811475637444243
            ],
            "footprint_cost": 0.0,
            "min_dist_to_obstacle": 0.7433034484420097
        },
        {
            "pose": [
                1.682073158009618,
                1.8128778586155065,
                0.8811436182512197
            ],
            "footprint_cost": 0.0,
            "min_dist_to_obstacle": 0.6800735355706574
        },
        {
            "pose": [
                1.7271016679246003,
                1.8674700354102087,
                0.8811056767016526
            ],
            "footprint_cost": 0.0,
            "min_dist_to_obstacle": 0.6670832131466311
        },
        {
            "pose": [
                1.7721348365800351,
                1.9220579533919553,
                0.8810165967961326
            ],
            "footprint_cost": 0.0,
            "min_dist_to_obstacle": 0.6020797379113019
        },
        {
            "pose": [
                1.8171765521502634,
                1.9766362040331111,
                0.8808364917396982
            ],
            "footprint_cost": 0.0,
            "min_dist_to_obstacle": 0.5500000081956387
        },
        {
            "pose": [
                1.862234398048267,
                2.0311951860338975,
                0.8804873441385512
            ],
            "footprint_cost": 0.0,
            "min_dist_to_obstacle": 0.5000000074505806
        },
        {
            "pose": [
                1.907250984607632,
                2.085803144428614,
                0.8813775397694932
            ],
            "footprint_cost": 0.0,
            "min_dist_to_obstacle": 0.45000000670552254
        },
        {
            "pose": [
                1.9522671008335586,
                2.1404114909517595,
                0.8813861563162679
            ],
            "footprint_cost": 0.0,
            "min_dist_to_obstacle": 0.4031128934217776
        },
        {
            "pose": [
                1.9972832170594852,
                2.1950198374749057,
                0.8813861563162719
            ],
            "footprint_cost": 0.0,
            "min_dist_to_obstacle": 0.36400549988813047
        },
        {
            "pose": [
                2.0422993332854116,
                2.2496281839980514,
                0.8813861563162704
            ],
            "footprint_cost": 0.0,
            "min_dist_to_obstacle": 0.33541020162296986
        },
        {
            "pose": [
                2.087315449511338,
                2.304236530521197,
                0.8813861563162679
            ],
            "footprint_cost": 0.0,
            "min_dist_to_obstacle": 0.3162277707289989
        },
        {
            "pose": [
                2.132331565737265,
                2.358844877044343,
                0.8813861563162679
            ],
            "footprint_cost": 0.0,
            "min_dist_to_obstacle": 0.2915475990866627
        },
        {
            "pose": [
                2.177347681963191,
                2.4134532235674886,
                0.8813861563162727
            ],
            "footprint_cost": 0.0,
            "min_dist_to_obstacle": 0.32015621664234173
        },
        {
            "pose": [
                2.2223637981891176,
                2.4680615700906348,
                0.8813861563162719
            ],
            "footprint_cost": 0.0,
            "min_dist_to_obstacle": 0.32015621664234173
        },
        {
            "pose": [
                2.2675773459808757,
                2.5225035811680425,
                0.8777384097118307
            ],
            "footprint_cost": 0.0,
            "min_dist_to_obstacle": 0.38078866096738856
        },
        {
            "pose": [
                2.317922888290624,
                2.5721573062713343,
                0.7784800510205944
            ],
            "footprint_cost": 0.0,
            "min_dist_to_obstacle": 0.41231056870567223
        },
        {
            "pose": [
                2.374769594084784,
                2.614212247567788,
                0.6369382235623084
            ],
            "footprint_cost": 0.0,
            "min_dist_to_obstacle": 0.4031128934217776
        },
        {
            "pose": [
                2.4369804914905515,
                2.6478272782990704,
                0.4953963961040217
            ],
            "footprint_cost": 0.0,
            "min_dist_to_obstacle": 0.45000000670552254
        },
        {
            "pose": [
                2.5033113212400555,
                2.6723300755238424,
                0.3538545686457201
            ],
            "footprint_cost": 0.0,
            "min_dist_to_obstacle": 0.45000000670552254
        },
        {
            "pose": [
                2.5724354226821387,
                2.6872305670231365,
                0.2123127411874403
            ],
            "footprint_cost": 0.0,
            "min_dist_to_obstacle": 0.45000000670552254
        },
        {
            "pose": [
                2.642970267876535,
                2.6922307330702324,
                0.07077091372914476
            ],
            "footprint_cost": 0.0,
            "min_dist_to_obstacle": 0.45000000670552254
        }
    ],
    "path_with_controller": [
        {
            "pose": [
                0,
                0,
                0
            ],
            "footprint_cost": 0.0,
            "linear_velocity": [
                0.01718199914647115,
                0.0,
                0.0
            ],
            "angular_velocity": [
                0.0,
                0.0,
                -0.0022540306830706133
            ],
            "min_scan_value": 0.8118618726730347
        },
        {
            "pose": [
                0,
                0,
                0
            ],
            "footprint_cost": 0.0,
            "linear_velocity": [
                0.0649505949169292,
                0.0,
                0.0
            ],
            "angular_velocity": [
                0.0,
                0.0,
                0.03448272183357726
            ],
            "min_scan_value": 0.8013162612915039
        },
        {
            "pose": [
                0,
                0,
                0
            ],
            "footprint_cost": 0.0,
            "linear_velocity": [
                0.10412610964799227,
                0.0,
                0.0
            ],
            "angular_velocity": [
                0.0,
                0.0,
                0.09778532445381403
            ],
            "min_scan_value": 0.7943709492683411
        },
        {
            "pose": [
                0,
                0,
                0
            ],
            "footprint_cost": 0.0,
            "linear_velocity": [
                0.1373584453941327,
                0.0,
                0.0
            ],
            "angular_velocity": [
                0.0,
                0.0,
                0.17454323008687184
            ],
            "min_scan_value": 0.8186962604522705
        },
        {
            "pose": [
                0,
                0,
                0
            ],
            "footprint_cost": 0.0,
            "linear_velocity": [
                0.13025634585769158,
                0.0,
                0.0
            ],
            "angular_velocity": [
                0.0,
                0.0,
                0.26994591936257734
            ],
            "min_scan_value": 0.8088659644126892
        },
        {
            "pose": [
                0,
                0,
                0
            ],
            "footprint_cost": 0.0,
            "linear_velocity": [
                0.1268194466713804,
                0.0,
                0.0
            ],
            "angular_velocity": [
                0.0,
                0.0,
                0.3425977288218803
            ],
            "min_scan_value": 0.8354859948158264
        },
        {
            "pose": [
                0,
                0,
                0
            ],
            "footprint_cost": 0.0,
            "linear_velocity": [
                0.13968120514047663,
                0.0,
                0.0
            ],
            "angular_velocity": [
                0.0,
                0.0,
                0.39684489355568486
            ],
            "min_scan_value": 0.8454789519309998
        },
        {
            "pose": [
                0.13367569145872815,
                0.014161612721269189,
                0.2777570406903694
            ],
            "footprint_cost": 0.0,
            "linear_velocity": [
                0.15506797431563638,
                0.0,
                0.0
            ],
            "angular_velocity": [
                0.0,
                0.0,
                0.43615432964348866
            ],
            "min_scan_value": 0.8599598407745361
        },
        {
            "pose": [
                0.13367569145872815,
                0.014161612721269189,
                0.2777570406903694
            ],
            "footprint_cost": 0.0,
            "linear_velocity": [
                0.18133496491726797,
                0.0,
                0.0
            ],
            "angular_velocity": [
                0.0,
                0.0,
                0.45871795701369394
            ],
            "min_scan_value": 0.8633821606636047
        },
        {
            "pose": [
                0.13367569145872815,
                0.014161612721269189,
                0.2777570406903694
            ],
            "footprint_cost": 0.0,
            "linear_velocity": [
                0.20637090204658506,
                0.0,
                0.0
            ],
            "angular_velocity": [
                0.0,
                0.0,
                0.46527372587191673
            ],
            "min_scan_value": 0.8947150111198425
        },
        {
            "pose": [
                0.23556538426333345,
                0.06399061160975013,
                0.554634895967677
            ],
            "footprint_cost": 0.0,
            "linear_velocity": [
                0.23586143003336915,
                0.0,
                0.0
            ],
            "angular_velocity": [
                0.0,
                0.0,
                0.451071691409652
            ],
            "min_scan_value": 0.9280110597610474
        },
        {
            "pose": [
                0.23556538426333345,
                0.06399061160975013,
                0.554634895967677
            ],
            "footprint_cost": 0.0,
            "linear_velocity": [
                0.27122373627027824,
                0.0,
                0.0
            ],
            "angular_velocity": [
                0.0,
                0.0,
                0.42145909657712954
            ],
            "min_scan_value": 0.9790725111961365
        },
        {
            "pose": [
                0.23556538426333345,
                0.06399061160975013,
                0.554634895967677
            ],
            "footprint_cost": 0.0,
            "linear_velocity": [
                0.3107664977153568,
                0.0,
                0.0
            ],
            "angular_velocity": [
                0.0,
                0.0,
                0.3782375454055361
            ],
            "min_scan_value": 1.0273759365081787
        },
        {
            "pose": [
                0.3635623431405022,
                0.1646058436744233,
                0.7952014572137261
            ],
            "footprint_cost": 0.0,
            "linear_velocity": [
                0.3580324783146954,
                0.0,
                0.0
            ],
            "angular_velocity": [
                0.0,
                0.0,
                0.31889946453814055
            ],
            "min_scan_value": 1.0952057838439941
        },
        {
            "pose": [
                0.3635623431405022,
                0.1646058436744233,
                0.7952014572137261
            ],
            "footprint_cost": 0.0,
            "linear_velocity": [
                0.3992132260621001,
                0.0,
                0.0
            ],
            "angular_velocity": [
                0.0,
                0.0,
                0.2622046708460287
            ],
            "min_scan_value": 1.1498345136642456
        },
        {
            "pose": [
                0.3635623431405022,
                0.1646058436744233,
                0.7952014572137261
            ],
            "footprint_cost": 0.0,
            "linear_velocity": [
                0.4377395584411065,
                0.0,
                0.0
            ],
            "angular_velocity": [
                0.0,
                0.0,
                0.19700958127201862
            ],
            "min_scan_value": 1.2496005296707153
        },
        {
            "pose": [
                0.3635623431405022,
                0.1646058436744233,
                0.7952014572137261
            ],
            "footprint_cost": 0.0,
            "linear_velocity": [
                0.4723704402279994,
                0.0,
                0.0
            ],
            "angular_velocity": [
                0.0,
                0.0,
                0.1293917372302376
            ],
            "min_scan_value": 1.342564344406128
        },
        {
            "pose": [
                0.5774295253291014,
                0.42599115431406004,
                0.9478290508547605
            ],
            "footprint_cost": 0.0,
            "linear_velocity": [
                0.4982457702002729,
                0.0,
                0.0
            ],
            "angular_velocity": [
                0.0,
                0.0,
                0.0645487307989962
            ],
            "min_scan_value": 1.4248543977737427
        },
        {
            "pose": [
                0.5774295253291014,
                0.42599115431406004,
                0.9478290508547605
            ],
            "footprint_cost": 0.0,
            "linear_velocity": [
                0.49999999998571293,
                0.0,
                0.0
            ],
            "angular_velocity": [
                0.0,
                0.0,
                0.01210591377927382
            ],
            "min_scan_value": 1.5397368669509888
        },
        {
            "pose": [
                0.5774295253291014,
                0.42599115431406004,
                0.9478290508547605
            ],
            "footprint_cost": 0.0,
            "linear_velocity": [
                0.49999999998572625,
                0.0,
                0.0
            ],
            "angular_velocity": [
                0.0,
                0.0,
                -0.03353865211184337
            ],
            "min_scan_value": 1.6381608247756958
        },
        {
            "pose": [
                0.5774295253291014,
                0.42599115431406004,
                0.9478290508547605
            ],
            "footprint_cost": 0.0,
            "linear_velocity": [
                0.4999999999857064,
                0.0,
                0.0
            ],
            "angular_velocity": [
                0.0,
                0.0,
                -0.06673852195448708
            ],
            "min_scan_value": 1.743033766746521
        },
        {
            "pose": [
                0.7939005579322783,
                0.7572239922853878,
                0.9706311997177578
            ],
            "footprint_cost": 0.0,
            "linear_velocity": [
                0.49999999998566524,
                0.0,
                0.0
            ],
            "angular_velocity": [
                0.0,
                0.0,
                -0.09030612250542465
            ],
            "min_scan_value": 1.8390752077102661
        },
        {
            "pose": [
                0.7939005579322783,
                0.7572239922853878,
                0.9706311997177578
            ],
            "footprint_cost": 0.0,
            "linear_velocity": [
                0.4999988078927231,
                0.0,
                0.0
            ],
            "angular_velocity": [
                0.0,
                0.0,
                -0.07173323622336478
            ],
            "min_scan_value": 1.9443837404251099
        },
        {
            "pose": [
                0.7939005579322783,
                0.7572239922853878,
                0.9706311997177578
            ],
            "footprint_cost": 0.0,
            "linear_velocity": [
                0.49999994038097517,
                0.0,
                0.0
            ],
            "angular_velocity": [
                0.0,
                0.0,
                -0.053389891890123595
            ],
            "min_scan_value": 1.8657268285751343
        },
        {
            "pose": [
                0.7939005579322783,
                0.7572239922853878,
                0.9706311997177578
            ],
            "footprint_cost": 0.0,
            "linear_velocity": [
                0.4999999403809552,
                0.0,
                0.0
            ],
            "angular_velocity": [
                0.0,
                0.0,
                -0.04408879941721271
            ],
            "min_scan_value": 1.7672369480133057
        },
        {
            "pose": [
                1.0280821022294715,
                1.0532875912343163,
                0.8977667112294976
            ],
            "footprint_cost": 0.0,
            "linear_velocity": [
                0.49999994038096407,
                0.0,
                0.0
            ],
            "angular_velocity": [
                0.0,
                0.0,
                -0.03869604123884777
            ],
            "min_scan_value": 1.6702525615692139
        },
        {
            "pose": [
                1.0280821022294715,
                1.0532875912343163,
                0.8977667112294976
            ],
            "footprint_cost": 0.0,
            "linear_velocity": [
                0.49999994038092854,
                0.0,
                0.0
            ],
            "angular_velocity": [
                0.0,
                0.0,
                -0.06737261256657082
            ],
            "min_scan_value": 1.5563796758651733
        },
        {
            "pose": [
                1.0280821022294715,
                1.0532875912343163,
                0.8977667112294976
            ],
            "footprint_cost": 0.0,
            "linear_velocity": [
                0.4999999403809263,
                0.0,
                0.0
            ],
            "angular_velocity": [
                0.0,
                0.0,
                -0.07678018054581535
            ],
            "min_scan_value": 1.4532278776168823
        },
        {
            "pose": [
                1.0280821022294715,
                1.0532875912343163,
                0.8977667112294976
            ],
            "footprint_cost": 0.0,
            "linear_velocity": [
                0.49999994038090634,
                0.0,
                0.0
            ],
            "angular_velocity": [
                0.0,
                0.0,
                -0.07357041529361333
            ],
            "min_scan_value": 1.3640692234039307
        },
        {
            "pose": [
                1.265610615059838,
                1.3215611522795503,
                0.8440214400013666
            ],
            "footprint_cost": 0.0,
            "linear_velocity": [
                0.4999999403808886,
                0.0,
                0.0
            ],
            "angular_velocity": [
                0.0,
                0.0,
                -0.06362278751296668
            ],
            "min_scan_value": 1.2538509368896484
        },
        {
            "pose": [
                1.265610615059838,
                1.3215611522795503,
                0.8440214400013666
            ],
            "footprint_cost": 0.0,
            "linear_velocity": [
                0.49999994038088635,
                0.0,
                0.0
            ],
            "angular_velocity": [
                0.0,
                0.0,
                -0.013046231041002169
            ],
            "min_scan_value": 1.165084719657898
        },
        {
            "pose": [
                1.265610615059838,
                1.3215611522795503,
                0.8440214400013666
            ],
            "footprint_cost": 0.0,
            "linear_velocity": [
                0.49999994038088413,
                0.0,
                0.0
            ],
            "angular_velocity": [
                0.0,
                0.0,
                0.02179884027588752
            ],
            "min_scan_value": 1.061537742614746
        },
        {
            "pose": [
                1.265610615059838,
                1.3215611522795503,
                0.8440214400013666
            ],
            "footprint_cost": 0.0,
            "linear_velocity": [
                0.49999995826228716,
                0.0,
                0.0
            ],
            "angular_velocity": [
                0.0,
                0.0,
                0.04891218684564488
            ],
            "min_scan_value": 0.9774827361106873
        },
        {
            "pose": [
                1.5222808471124025,
                1.5760499108623987,
                0.8409327846934125
            ],
            "footprint_cost": 0.0,
            "linear_velocity": [
                0.4999999999855653,
                0.0,
                0.0
            ],
            "angular_velocity": [
                0.0,
                0.0,
                0.05783070616590531
            ],
            "min_scan_value": 0.870954692363739
        },
        {
            "pose": [
                1.5222808471124025,
                1.5760499108623987,
                0.8409327846934125
            ],
            "footprint_cost": 0.0,
            "linear_velocity": [
                0.4999999999855653,
                0.0,
                0.0
            ],
            "angular_velocity": [
                0.0,
                0.0,
                0.07107110761482857
            ],
            "min_scan_value": 0.7839893698692322
        },
        {
            "pose": [
                1.5222808471124025,
                1.5760499108623987,
                0.8409327846934125
            ],
            "footprint_cost": 0.0,
            "linear_velocity": [
                0.49999999998557865,
                0.0,
                0.0
            ],
            "angular_velocity": [
                0.0,
                0.0,
                0.06480141349962959
            ],
            "min_scan_value": 0.6889781355857849
        },
        {
            "pose": [
                1.5222808471124025,
                1.5760499108623987,
                0.8409327846934125
            ],
            "footprint_cost": 0.0,
            "linear_velocity": [
                0.4999999999856053,
                0.0,
                0.0
            ],
            "angular_velocity": [
                0.0,
                0.0,
                0.029950765827447524
            ],
            "min_scan_value": 0.6113631129264832
        },
        {
            "pose": [
                1.7781326270460467,
                1.8611540918648353,
                0.8853795413578504
            ],
            "footprint_cost": 0.0,
            "linear_velocity": [
                0.4999999999855742,
                0.0,
                0.0
            ],
            "angular_velocity": [
                0.0,
                0.0,
                -0.0016757016093644768
            ],
            "min_scan_value": 0.5069471001625061
        },
        {
            "pose": [
                1.7781326270460467,
                1.8611540918648353,
                0.8853795413578504
            ],
            "footprint_cost": 0.0,
            "linear_velocity": [
                0.4999999999855831,
                0.0,
                0.0
            ],
            "angular_velocity": [
                0.0,
                0.0,
                -0.02633119402734796
            ],
            "min_scan_value": 0.42435961961746216
        },
        {
            "pose": [
                1.7781326270460467,
                1.8611540918648353,
                0.8853795413578504
            ],
            "footprint_cost": 0.0,
            "linear_velocity": [
                0.49976747034550684,
                0.0,
                0.0
            ],
            "angular_velocity": [
                0.0,
                0.0,
                -0.047331694423925944
            ],
            "min_scan_value": 0.36637943983078003
        },
        {
            "pose": [
                1.7781326270460467,
                1.8611540918648353,
                0.8853795413578504
            ],
            "footprint_cost": 0.0,
            "linear_velocity": [
                0.49321927426833945,
                0.0,
                0.0
            ],
            "angular_velocity": [
                0.0,
                0.0,
                -0.0647827177360539
            ],
            "min_scan_value": 0.3124062120914459
        },
        {
            "pose": [
                2.0535473659451977,
                2.163986766733489,
                0.8416189144467289
            ],
            "footprint_cost": 0.0,
            "linear_velocity": [
                0.4825758158858262,
                0.0,
                0.0
            ],
            "angular_velocity": [
                0.0,
                0.0,
                -0.10272081588700008
            ],
            "min_scan_value": 0.30384427309036255
        },
        {
            "pose": [
                2.0535473659451977,
                2.163986766733489,
                0.8416189144467289
            ],
            "footprint_cost": 0.0,
            "linear_velocity": [
                0.4765610843342749,
                0.0,
                0.0
            ],
            "angular_velocity": [
                0.0,
                0.0,
                -0.16426131924335677
            ],
            "min_scan_value": 0.28369781374931335
        },
        {
            "pose": [
                2.0535473659451977,
                2.163986766733489,
                0.8416189144467289
            ],
            "footprint_cost": 0.0,
            "linear_velocity": [
                0.4637740104940935,
                0.0,
                0.0
            ],
            "angular_velocity": [
                0.0,
                0.0,
                -0.19756970591506323
            ],
            "min_scan_value": 0.2527717053890228
        },
        {
            "pose": [
                2.0535473659451977,
                2.163986766733489,
                0.8416189144467289
            ],
            "footprint_cost": 0.0,
            "linear_velocity": [
                0.44377326961670516,
                0.0,
                0.0
            ],
            "angular_velocity": [
                0.0,
                0.0,
                -0.22405274924190843
            ],
            "min_scan_value": 0.22382614016532898
        },
        {
            "pose": [
                2.3647848793451565,
                2.3852594406138667,
                0.5958659949358893
            ],
            "footprint_cost": 254.0,
            "linear_velocity": [
                0.42021347880397464,
                0.0,
                0.0
            ],
            "angular_velocity": [
                0.0,
                0.0,
                -0.2454181194303166
            ],
            "min_scan_value": 0.22762995958328247
        }
    ],
    "task_result": "failed",
    "iteration_num": 1182,
    "is_collided": true,
    "global_path_length": 3.8754589566759217,
    "local_path_length": 3.4156192712650206,
    "duration_of_moving": 9.294633150100708,
    "min_dist_to_obstacle": 0.2915475990866627
}